{
  "url": "https://guiadeconteudo.blog/movie/NzE1MTg=",
  "tipo": "filme",
  "capa_url": "https://lgfp.one/LCL",
  "sinopse": "A viagem relaxante de Barry Allen para Metr?polis est? prestes a dar errado. Enquanto corre para ajudar em uma luta inesperada, o Flash rompe as barreiras do tempo, e acaba parando no meio da Segunda Guerra Mundial. ? l? que o Flash conhece a Mulher Maravilha e a equipe supersecreta dela, conhecida como Sociedade da Justi?a da Am?rica. Testemunhe os rumos turbulentos da guerra, combates envolventes e a velocidade da honra enquanto o Flash luta para voltar ao seu pr?prio tempo!",
  "genero": "ANIMA??O, GUERRA, FIC??O CIENT?FICA",
  "ano": "",
  "duracao": "01:24:00",
  "elenco": "Stana Katic, Matt Bomer, Chris Diamantopoulos, Darren Criss, Elysia Rotaru, Omid Abtahi, Armen Taylor",
  "diretor": "Jeff Wamester",
  "titulo": "SOCIEDADE DA JUSTIÇA: 2ª GUERRA MUNDIAL",
  "id": 66646,
  "qualidade": "FHD",
  "capa_local": "SOCIEDADE DA JUSTICA 2a GUERRA MUNDIAL/SOCIEDADE DA JUSTICA 2a GUERRA MUNDIAL.jpg"
}