{
  "url": "https://guiadeconteudo.blog/movie/NzQ1ODE=",
  "tipo": "filme",
  "capa_url": "https://lgfp.one/OWO",
  "sinopse": "Uma s?rie de contratempos amea?a a tentativa de uma m?e, rec?m-divorciada, tornar perfeito o primeiro Natal sem o pai.",
  "genero": "COM?DIA, DRAMA, FAM?LIA, CINEMA TV",
  "ano": "",
  "duracao": "01:27:29",
  "elenco": "Anne Heche, Carlos G?mez, Kevin Daniels, Brian Tee, Alissa Skovbye, Tracy Waterhouse, Kiana Madeira",
  "diretor": "Jay Russell",
  "titulo": "UMA NOITE DE NATAL",
  "id": 102797,
  "qualidade": "FHD",
  "capa_local": "UMA NOITE DE NATAL/UMA NOITE DE NATAL.jpg"
}