{
  "url": "https://guiadeconteudo.blog/serie/OTQ1MjE=",
  "tipo": "serie",
  "titulo": "BOKU NO HERO ACADEMIA [L]",
  "capa_url": "https://lgfp.one/BDT2",
  "capa_local": "BOKU NO HERO ACADEMIA [L]/BOKU NO HERO ACADEMIA [L].jpg",
  "sinopse": "Por toda a sua vida, Izuku sonhou ser um herói — um objetivo ambicioso para qualquer um, mas especialmente desafiador para um garoto sem superpoderes. Isso mesmo: em um mundo onde 80% da população tem algum tipo de Dom especial, Izuku teve a má sorte de nascer completamente normal. Mas isso não vai impedi-lo de se matricular em uma das academias de herois mais prestigiosas do mundo.",
  "genero": "Action & Adventure, Animação, Sci-Fi & Fantasy",
  "elenco": "",
  "diretor": "中山奈緒美, 長崎健司",
  "total_episodios": "24",
  "temporadas": [
    {
      "temporada": "TEMPORADA: 1",
      "episodios": [
        {
          "numero": "1",
          "codigo": "S01E01",
          "duracao": "00:24:32"
        },
        {
          "numero": "2",
          "codigo": "S01E02",
          "duracao": "00:24:31"
        },
        {
          "numero": "3",
          "codigo": "S01E03",
          "duracao": "00:24:31"
        },
        {
          "numero": "4",
          "codigo": "S01E04",
          "duracao": "00:24:32"
        },
        {
          "numero": "5",
          "codigo": "S01E05",
          "duracao": "00:24:31"
        },
        {
          "numero": "6",
          "codigo": "S01E06",
          "duracao": "00:24:31"
        },
        {
          "numero": "7",
          "codigo": "S01E07",
          "duracao": "00:24:17"
        },
        {
          "numero": "8",
          "codigo": "S01E08",
          "duracao": "00:24:15"
        },
        {
          "numero": "9",
          "codigo": "S01E09",
          "duracao": "00:24:16"
        },
        {
          "numero": "10",
          "codigo": "S01E10",
          "duracao": "00:24:16"
        },
        {
          "numero": "11",
          "codigo": "S01E11",
          "duracao": "00:24:16"
        },
        {
          "numero": "12",
          "codigo": "S01E12",
          "duracao": "00:24:17"
        },
        {
          "numero": "13",
          "codigo": "S01E13",
          "duracao": "00:24:17"
        }
      ]
    },
    {
      "temporada": "TEMPORADA: 2",
      "episodios": [
        {
          "numero": "14",
          "codigo": "S02E14",
          "duracao": "00:23:50"
        },
        {
          "numero": "15",
          "codigo": "S02E15",
          "duracao": "00:23:50"
        },
        {
          "numero": "16",
          "codigo": "S02E16",
          "duracao": "00:23:50"
        },
        {
          "numero": "17",
          "codigo": "S02E17",
          "duracao": "00:23:50"
        },
        {
          "numero": "18",
          "codigo": "S02E18",
          "duracao": "00:23:50"
        },
        {
          "numero": "19",
          "codigo": "S02E19",
          "duracao": "00:23:50"
        },
        {
          "numero": "20",
          "codigo": "S02E20",
          "duracao": "00:23:50"
        },
        {
          "numero": "21",
          "codigo": "S02E21",
          "duracao": "00:23:50"
        },
        {
          "numero": "22",
          "codigo": "S02E22",
          "duracao": "00:23:50"
        },
        {
          "numero": "23",
          "codigo": "S02E23",
          "duracao": "00:23:49"
        },
        {
          "numero": "24",
          "codigo": "S02E24",
          "duracao": "00:23:49"
        },
        {
          "numero": "25",
          "codigo": "S02E25",
          "duracao": "00:23:49"
        },
        {
          "numero": "26",
          "codigo": "S02E26",
          "duracao": "00:23:49"
        },
        {
          "numero": "27",
          "codigo": "S02E27",
          "duracao": "00:23:49"
        },
        {
          "numero": "28",
          "codigo": "S02E28",
          "duracao": "00:23:50"
        },
        {
          "numero": "29",
          "codigo": "S02E29",
          "duracao": "00:23:50"
        },
        {
          "numero": "30",
          "codigo": "S02E30",
          "duracao": "00:23:50"
        },
        {
          "numero": "31",
          "codigo": "S02E31",
          "duracao": "00:23:49"
        },
        {
          "numero": "32",
          "codigo": "S02E32",
          "duracao": "00:23:50"
        },
        {
          "numero": "33",
          "codigo": "S02E33",
          "duracao": "00:23:50"
        },
        {
          "numero": "34",
          "codigo": "S02E34",
          "duracao": "00:23:50"
        },
        {
          "numero": "35",
          "codigo": "S02E35",
          "duracao": "00:23:49"
        },
        {
          "numero": "36",
          "codigo": "S02E36",
          "duracao": "00:23:49"
        },
        {
          "numero": "37",
          "codigo": "S02E37",
          "duracao": "00:23:49"
        },
        {
          "numero": "38",
          "codigo": "S02E38",
          "duracao": "00:23:20"
        }
      ]
    },
    {
      "temporada": "TEMPORADA: 3",
      "episodios": [
        {
          "numero": "39",
          "codigo": "S03E39",
          "duracao": "00:23:52"
        },
        {
          "numero": "40",
          "codigo": "S03E40",
          "duracao": "00:23:51"
        },
        {
          "numero": "41",
          "codigo": "S03E41",
          "duracao": "00:23:52"
        },
        {
          "numero": "42",
          "codigo": "S03E42",
          "duracao": "00:23:52"
        },
        {
          "numero": "43",
          "codigo": "S03E43",
          "duracao": "00:23:52"
        },
        {
          "numero": "44",
          "codigo": "S03E44",
          "duracao": "00:23:52"
        },
        {
          "numero": "45",
          "codigo": "S03E45",
          "duracao": "00:23:52"
        },
        {
          "numero": "46",
          "codigo": "S03E46",
          "duracao": "00:23:52"
        },
        {
          "numero": "47",
          "codigo": "S03E47",
          "duracao": "00:23:52"
        },
        {
          "numero": "48",
          "codigo": "S03E48",
          "duracao": "00:23:51"
        },
        {
          "numero": "49",
          "codigo": "S03E49",
          "duracao": "00:23:52"
        },
        {
          "numero": "50",
          "codigo": "S03E50",
          "duracao": "00:23:51"
        },
        {
          "numero": "51",
          "codigo": "S03E51",
          "duracao": "00:23:52"
        },
        {
          "numero": "52",
          "codigo": "S03E52",
          "duracao": "00:23:52"
        },
        {
          "numero": "53",
          "codigo": "S03E53",
          "duracao": "00:23:52"
        },
        {
          "numero": "54",
          "codigo": "S03E54",
          "duracao": "00:23:52"
        },
        {
          "numero": "55",
          "codigo": "S03E55",
          "duracao": "00:23:52"
        },
        {
          "numero": "56",
          "codigo": "S03E56",
          "duracao": "00:23:52"
        },
        {
          "numero": "57",
          "codigo": "S03E57",
          "duracao": "00:23:52"
        },
        {
          "numero": "58",
          "codigo": "S03E58",
          "duracao": "00:23:52"
        },
        {
          "numero": "59",
          "codigo": "S03E59",
          "duracao": "00:23:52"
        },
        {
          "numero": "60",
          "codigo": "S03E60",
          "duracao": "00:23:52"
        },
        {
          "numero": "61",
          "codigo": "S03E61",
          "duracao": "00:23:52"
        },
        {
          "numero": "62",
          "codigo": "S03E62",
          "duracao": "00:23:52"
        },
        {
          "numero": "63",
          "codigo": "S03E63",
          "duracao": "00:23:36"
        }
      ]
    },
    {
      "temporada": "TEMPORADA: 4",
      "episodios": [
        {
          "numero": "64",
          "codigo": "S04E64",
          "duracao": "00:23:51"
        },
        {
          "numero": "65",
          "codigo": "S04E65",
          "duracao": "00:23:52"
        },
        {
          "numero": "66",
          "codigo": "S04E66",
          "duracao": "00:23:52"
        },
        {
          "numero": "67",
          "codigo": "S04E67",
          "duracao": "00:23:52"
        },
        {
          "numero": "68",
          "codigo": "S04E68",
          "duracao": "00:23:52"
        },
        {
          "numero": "69",
          "codigo": "S04E69",
          "duracao": "00:23:52"
        },
        {
          "numero": "70",
          "codigo": "S04E70",
          "duracao": "00:23:52"
        },
        {
          "numero": "71",
          "codigo": "S04E71",
          "duracao": "00:23:52"
        },
        {
          "numero": "72",
          "codigo": "S04E72",
          "duracao": "00:23:52"
        },
        {
          "numero": "73",
          "codigo": "S04E73",
          "duracao": "00:23:52"
        },
        {
          "numero": "74",
          "codigo": "S04E74",
          "duracao": "00:23:52"
        },
        {
          "numero": "75",
          "codigo": "S04E75",
          "duracao": "00:23:52"
        },
        {
          "numero": "76",
          "codigo": "S04E76",
          "duracao": "00:23:52"
        },
        {
          "numero": "77",
          "codigo": "S04E77",
          "duracao": "00:23:52"
        },
        {
          "numero": "78",
          "codigo": "S04E78",
          "duracao": "00:23:52"
        },
        {
          "numero": "79",
          "codigo": "S04E79",
          "duracao": "00:23:52"
        },
        {
          "numero": "80",
          "codigo": "S04E80",
          "duracao": "00:23:52"
        },
        {
          "numero": "81",
          "codigo": "S04E81",
          "duracao": "00:23:52"
        },
        {
          "numero": "82",
          "codigo": "S04E82",
          "duracao": "00:23:52"
        },
        {
          "numero": "83",
          "codigo": "S04E83",
          "duracao": "00:23:52"
        },
        {
          "numero": "84",
          "codigo": "S04E84",
          "duracao": "00:23:52"
        },
        {
          "numero": "85",
          "codigo": "S04E85",
          "duracao": "00:23:52"
        },
        {
          "numero": "86",
          "codigo": "S04E86",
          "duracao": "00:23:52"
        },
        {
          "numero": "87",
          "codigo": "S04E87",
          "duracao": "00:23:52"
        },
        {
          "numero": "88",
          "codigo": "S04E88",
          "duracao": "00:23:22"
        }
      ]
    },
    {
      "temporada": "TEMPORADA: 5",
      "episodios": [
        {
          "numero": "89",
          "codigo": "S05E89",
          "duracao": "00:23:50"
        },
        {
          "numero": "90",
          "codigo": "S05E90",
          "duracao": "00:23:50"
        },
        {
          "numero": "91",
          "codigo": "S05E91",
          "duracao": "00:23:49"
        },
        {
          "numero": "92",
          "codigo": "S05E92",
          "duracao": "00:23:50"
        },
        {
          "numero": "93",
          "codigo": "S05E93",
          "duracao": "00:23:50"
        },
        {
          "numero": "94",
          "codigo": "S05E94",
          "duracao": "00:23:50"
        },
        {
          "numero": "95",
          "codigo": "S05E95",
          "duracao": "00:23:50"
        },
        {
          "numero": "96",
          "codigo": "S05E96",
          "duracao": "00:23:50"
        },
        {
          "numero": "97",
          "codigo": "S05E97",
          "duracao": "00:23:50"
        },
        {
          "numero": "98",
          "codigo": "S05E98",
          "duracao": "00:23:50"
        },
        {
          "numero": "99",
          "codigo": "S05E99",
          "duracao": "00:23:50"
        },
        {
          "numero": "100",
          "codigo": "S05E100",
          "duracao": "00:23:50"
        },
        {
          "numero": "101",
          "codigo": "S05E101",
          "duracao": "00:23:50"
        },
        {
          "numero": "102",
          "codigo": "S05E102",
          "duracao": "00:23:50"
        },
        {
          "numero": "103",
          "codigo": "S05E103",
          "duracao": "00:23:50"
        },
        {
          "numero": "104",
          "codigo": "S05E104",
          "duracao": "00:23:50"
        },
        {
          "numero": "105",
          "codigo": "S05E105",
          "duracao": "00:23:50"
        },
        {
          "numero": "106",
          "codigo": "S05E106",
          "duracao": "00:23:50"
        },
        {
          "numero": "107",
          "codigo": "S05E107",
          "duracao": "00:23:50"
        },
        {
          "numero": "108",
          "codigo": "S05E108",
          "duracao": "00:23:50"
        },
        {
          "numero": "109",
          "codigo": "S05E109",
          "duracao": "00:23:50"
        },
        {
          "numero": "110",
          "codigo": "S05E110",
          "duracao": "00:23:50"
        },
        {
          "numero": "111",
          "codigo": "S05E111",
          "duracao": "00:23:50"
        },
        {
          "numero": "112",
          "codigo": "S05E112",
          "duracao": "00:23:50"
        },
        {
          "numero": "113",
          "codigo": "S05E113",
          "duracao": "00:23:16"
        }
      ]
    },
    {
      "temporada": "TEMPORADA: 6",
      "episodios": [
        {
          "numero": "114",
          "codigo": "S06E114",
          "duracao": "00:23:50"
        },
        {
          "numero": "115",
          "codigo": "S06E115",
          "duracao": "00:23:50"
        },
        {
          "numero": "116",
          "codigo": "S06E116",
          "duracao": "00:23:50"
        },
        {
          "numero": "117",
          "codigo": "S06E117",
          "duracao": "00:23:50"
        },
        {
          "numero": "118",
          "codigo": "S06E118",
          "duracao": "00:23:50"
        },
        {
          "numero": "119",
          "codigo": "S06E119",
          "duracao": "00:23:50"
        },
        {
          "numero": "120",
          "codigo": "S06E120",
          "duracao": "00:23:50"
        },
        {
          "numero": "121",
          "codigo": "S06E121",
          "duracao": "00:23:50"
        },
        {
          "numero": "122",
          "codigo": "S06E122",
          "duracao": "00:23:50"
        },
        {
          "numero": "123",
          "codigo": "S06E123",
          "duracao": "00:23:50"
        },
        {
          "numero": "124",
          "codigo": "S06E124",
          "duracao": "00:23:50"
        },
        {
          "numero": "125",
          "codigo": "S06E125",
          "duracao": "00:23:50"
        },
        {
          "numero": "126",
          "codigo": "S06E126",
          "duracao": "00:23:50"
        },
        {
          "numero": "127",
          "codigo": "S06E127",
          "duracao": "00:23:50"
        },
        {
          "numero": "128",
          "codigo": "S06E128",
          "duracao": "00:23:50"
        },
        {
          "numero": "129",
          "codigo": "S06E129",
          "duracao": "00:23:50"
        },
        {
          "numero": "130",
          "codigo": "S06E130",
          "duracao": "00:23:50"
        },
        {
          "numero": "131",
          "codigo": "S06E131",
          "duracao": "00:23:50"
        },
        {
          "numero": "132",
          "codigo": "S06E132",
          "duracao": "00:23:50"
        },
        {
          "numero": "133",
          "codigo": "S06E133",
          "duracao": "00:23:50"
        },
        {
          "numero": "134",
          "codigo": "S06E134",
          "duracao": "00:23:50"
        },
        {
          "numero": "135",
          "codigo": "S06E135",
          "duracao": "00:23:50"
        },
        {
          "numero": "136",
          "codigo": "S06E136",
          "duracao": "00:23:50"
        },
        {
          "numero": "137",
          "codigo": "S06E137",
          "duracao": "00:23:50"
        },
        {
          "numero": "138",
          "codigo": "S06E138",
          "duracao": "00:23:20"
        }
      ]
    },
    {
      "temporada": "TEMPORADA: 7",
      "episodios": [
        {
          "numero": "139",
          "codigo": "S07E139",
          "duracao": "00:23:50"
        },
        {
          "numero": "140",
          "codigo": "S07E140",
          "duracao": "00:23:49"
        },
        {
          "numero": "141",
          "codigo": "S07E141",
          "duracao": "00:23:50"
        },
        {
          "numero": "142",
          "codigo": "S07E142",
          "duracao": "00:23:50"
        },
        {
          "numero": "143",
          "codigo": "S07E143",
          "duracao": "00:23:50"
        },
        {
          "numero": "144",
          "codigo": "S07E144",
          "duracao": "00:23:50"
        },
        {
          "numero": "145",
          "codigo": "S07E145",
          "duracao": "00:23:50"
        },
        {
          "numero": "146",
          "codigo": "S07E146",
          "duracao": "00:23:50"
        },
        {
          "numero": "147",
          "codigo": "S07E147",
          "duracao": "00:23:50"
        },
        {
          "numero": "148",
          "codigo": "S07E148",
          "duracao": "00:23:50"
        },
        {
          "numero": "149",
          "codigo": "S07E149",
          "duracao": "00:23:50"
        },
        {
          "numero": "150",
          "codigo": "S07E150",
          "duracao": "00:23:50"
        },
        {
          "numero": "151",
          "codigo": "S07E151",
          "duracao": "00:23:50"
        },
        {
          "numero": "152",
          "codigo": "S07E152",
          "duracao": "00:23:49"
        },
        {
          "numero": "153",
          "codigo": "S07E153",
          "duracao": "00:23:50"
        },
        {
          "numero": "154",
          "codigo": "S07E154",
          "duracao": "00:23:50"
        },
        {
          "numero": "155",
          "codigo": "S07E155",
          "duracao": "00:23:50"
        },
        {
          "numero": "156",
          "codigo": "S07E156",
          "duracao": "00:23:50"
        },
        {
          "numero": "157",
          "codigo": "S07E157",
          "duracao": "00:23:49"
        },
        {
          "numero": "158",
          "codigo": "S07E158",
          "duracao": "00:23:49"
        },
        {
          "numero": "159",
          "codigo": "S07E159",
          "duracao": "00:23:20"
        },
        {
          "numero": "160",
          "codigo": "S07E160",
          "duracao": "00:23:49"
        }
      ]
    },
    {
      "temporada": "TEMPORADA: 8",
      "episodios": [
        {
          "numero": "1",
          "codigo": "S08E01",
          "duracao": "00:23:50"
        },
        {
          "numero": "2",
          "codigo": "S08E02",
          "duracao": "00:23:50"
        },
        {
          "numero": "3",
          "codigo": "S08E03",
          "duracao": "00:23:50"
        },
        {
          "numero": "4",
          "codigo": "S08E04",
          "duracao": "00:23:50"
        },
        {
          "numero": "5",
          "codigo": "S08E05",
          "duracao": "00:23:50"
        },
        {
          "numero": "6",
          "codigo": "S08E06",
          "duracao": "00:23:50"
        },
        {
          "numero": "7",
          "codigo": "S08E07",
          "duracao": "00:23:50"
        },
        {
          "numero": "8",
          "codigo": "S08E08",
          "duracao": "00:23:50"
        },
        {
          "numero": "9",
          "codigo": "S08E09",
          "duracao": "00:23:50"
        },
        {
          "numero": "10",
          "codigo": "S08E10",
          "duracao": "00:23:50"
        },
        {
          "numero": "11",
          "codigo": "S08E11",
          "duracao": "00:23:20"
        }
      ]
    }
  ],
  "id": 227523
}