{
  "url": "https://guiadeconteudo.blog/movie/NjMyMTY=",
  "tipo": "filme",
  "capa_url": "https://lgfp.one/NQQ6",
  "sinopse": "Maxime (Medi Sadoun) ? um grande jogador de futebol que acaba de sofrer uma les?o. Sua agente o obriga a se recuperar em sua cidade natal, onde ele reencontra o pai que n?o v? h? anos e conhece uma nova equipe formada por crian?as muito bagunceiras.",
  "genero": "COM?DIA",
  "ano": "2016",
  "duracao": "01:37:08",
  "elenco": "Medi Sadoun, G?rard Depardieu, Chantal Lauby, Barbara Cabrita, Patrick Timsit",
  "diretor": "Thomas Sorriaux, Thomas Sorriaux, Cl?ment Michel",
  "titulo": "UM TIME BEM DIFERENTE",
  "id": 301970,
  "qualidade": "FHD",
  "capa_local": "UM TIME BEM DIFERENTE/UM TIME BEM DIFERENTE.jpg"
}