{
  "url": "https://guiadeconteudo.blog/movie/NTE1NTc=",
  "tipo": "filme",
  "capa_url": "https://lgfp.one/SEQ6",
  "sinopse": "Nishimiya Shouko é uma estudante com deficiência auditiva. Durante o ensino fundamental, após se transferir para uma nova escola, Shouko passa a ser alvo de bullying e em pouco tempo precisa se transferir. O que ela não esperava é que alguns anos depois, Ishida Shouya, um dos valentões que tanto a fez sofrer no passado surgisse de novo em sua vida com um novo propósito.",
  "genero": "ANIMAÇÃO, DRAMA, ROMANCE",
  "ano": "2016",
  "duracao": "02:09:45",
  "elenco": "Miyu Irino, Saori Hayami, Aoi Yuki, Kensho Ono, 金子有希",
  "diretor": "Yasuhiro Takemoto, 藤田春香, 石原立也",
  "titulo": "A VOZ DO SILÊNCIO [L]",
  "id": 375013,
  "qualidade": "FHD",
  "capa_local": "A VOZ DO SILENCIO [L]/A VOZ DO SILENCIO [L].jpg"
}