{
  "url": "https://guiadeconteudo.blog/movie/NjY5NjE=",
  "tipo": "filme",
  "capa_url": "https://lgfp.one/PRD",
  "sinopse": "Luccas Neto e Gi s?o convidados por Camila para passar as f?rias em um Hotel M?gico. O que n?o imaginam ? que o Elfo Mizinho tem um plano maluco: transform?-los em ratinhos para sempre. Ser? que conseguir?o escapar dessa armadilha felpuda?",
  "genero": "FAM?LIA, FANTASIA, COM?DIA, M?SICA",
  "ano": "",
  "duracao": "",
  "elenco": "Luccas Neto, Giovanna Alparone, Beta Brito, Rafael Chapouto, Vivian Duarte, Cleber Salgado, Roberta Piragibe",
  "diretor": "Lucas Margutti",
  "titulo": "LUCCAS NETO EM: O HOTEL MÁGICO 2",
  "id": 108340,
  "qualidade": "FHD",
  "capa_local": "LUCCAS NETO EM O HOTEL MAGICO 2/LUCCAS NETO EM O HOTEL MAGICO 2.jpg"
}