{
  "url": "https://guiadeconteudo.blog/movie/NjQ5MDQ=",
  "tipo": "filme",
  "capa_url": "https://lgfp.one/HHZ",
  "sinopse": "MILFGênero:COM?DIADuração:01:41:50Elenco:Jack Cullison, Philip Marlatt, Joseph Booton, Ramon Camacho, Amy Lindsay, Molinee Green, Rachel RileyDiretor:Scott WheelerCategoria:ComediaDisponível emiOSAndroidWindowsmacOSLinuxWebPlayStationXboxSmart TV",
  "genero": "COM?DIA",
  "ano": "",
  "duracao": "01:41:50",
  "elenco": "Jack Cullison, Philip Marlatt, Joseph Booton, Ramon Camacho, Amy Lindsay, Molinee Green, Rachel Riley",
  "diretor": "Scott Wheeler",
  "titulo": "MILF",
  "id": 35069,
  "qualidade": "FHD",
  "capa_local": "MILF/MILF.jpg"
}