{
  "url": "https://guiadeconteudo.blog/movie/NzEzNTc=",
  "tipo": "filme",
  "capa_url": "https://lgfp.one/XVE",
  "sinopse": "Num futuro p?s-apocal?ptico, uma pesquisadora lidera os esfor?os de p?r fim a uma guerra civil. Para isso, clona o c?rebro de uma destemida capit? do ex?rcito: sua m?e.",
  "genero": "FIC??O CIENT?FICA",
  "ano": "",
  "duracao": "01:39:45",
  "elenco": "???, ???, ???, ???, ???, ???, Lee Ga-kyung",
  "diretor": "???",
  "titulo": "JUNG_E",
  "id": 133121,
  "qualidade": "FHD",
  "capa_local": "JUNG_E/JUNG_E.jpg"
}