{
  "url": "https://guiadeconteudo.blog/movie/NTYwODY=",
  "tipo": "filme",
  "capa_url": "https://lgfp.one/AZC5",
  "sinopse": "Um alien?gena est? em busca de justi?a e persegue um criminoso desonesto em um planeta chamado Terra. Para expiar suas a??es, ele deixa o poder de transformar um humano em um her?i para proteger os humanos.",
  "genero": "A??O, FIC??O CIENT?FICA",
  "ano": "2022",
  "duracao": "01:52:16",
  "elenco": "???, ?????, Hidetoshi Nishijima, ????, ?????, ????, ????",
  "diretor": "Shinji Higuchi",
  "titulo": "SHIN ULTRAMAN [L]",
  "id": 204496,
  "qualidade": "FHD",
  "capa_local": "SHIN ULTRAMAN [L]/SHIN ULTRAMAN [L].jpg"
}