{
  "url": "https://guiadeconteudo.blog/movie/NTgzNTc=",
  "tipo": "filme",
  "capa_url": "https://lgfp.one/UUV",
  "sinopse": "Disposta a fazer o que for preciso para entrar na faculdade, a estudante Honor inventa um plano maquiav?lico para derrubar seus tr?s principais concorrentes. As coisas mudam quando ela inesperadamente se apaixona",
  "genero": "COM?DIA",
  "ano": "",
  "duracao": "01:37:52",
  "elenco": "Angourie Rice, Gaten Matarazzo, Christopher Mintz-Plasse, Armani Jackson, Amy Keum, Ben Jackson Walker, Kelcey Mawema",
  "diretor": "Oran Zegman",
  "titulo": "HONOR SOCIETY [L]",
  "id": 194251,
  "qualidade": "FHD",
  "capa_local": "HONOR SOCIETY [L]/HONOR SOCIETY [L].jpg"
}