{
  "url": "https://guiadeconteudo.blog/movie/NzQyMDc=",
  "tipo": "filme",
  "capa_url": "https://lgfp.one/MLU",
  "sinopse": "Cinco jovens da cidade de Nova Iorque planejam um fim de semana divertido na ?rea rural da Pensilvania. Contudo, algo amea?a estragar os seus planos: a fazenda, antiga propriedade da fam?lia de Nicole e local onde os seus pais morreram misteriosamente, encontra-se ocupada. O pre?o de reaver a antiga propriedade ser? alto. Uma abordagem moderna, sexy e divertida, num claro tributo ao g?nero do terror, este filme marca a estreia como diretora de Luciana Faulhaber, e desafia os pap?is cl?ssicos de homens e mulheres em pel?culas do tipo. Her?is improv?veis devem assumir a lideran?a e salvar o dia ? e a eles mesmos.",
  "genero": "TERROR",
  "ano": "",
  "duracao": "01:10:59",
  "elenco": "Luciana Faulhaber, Lindsay Eshelman, Javier E. G?mez, Jeff Berg, Curtis K Case, Hailey Heisick, Jarrod Robbins",
  "diretor": "Luciana Faulhaber",
  "titulo": "DON'T LOOK - A MORTE TE AGUARDA",
  "id": 90886,
  "qualidade": "FHD",
  "capa_local": "DON'T LOOK - A MORTE TE AGUARDA/DON'T LOOK - A MORTE TE AGUARDA.jpg"
}