{
  "url": "https://guiadeconteudo.blog/movie/Njk2NTM=",
  "tipo": "filme",
  "capa_url": "https://lgfp.one/LHL",
  "sinopse": "Em 1984, no South Central, bairro de maioria negra de Los Angeles, Reva Devereaux (Angela Bassett), m?e de Tre Styles (Cuba Gooding Jr.), conclui que n?o tem condi??es de criar o filho rebelde, mas inteligente. Reva decide entreg?-lo aos cuidados do pai, Furious Styles (Laurence Fishburne), que passa ao filho valores ?ticos e morais em uma regi?o marcada pelo pobreza e viol?ncia. Ap?s sete anos Tre faz dois grandes amigos: Ricky Baker (Morris Chestnut) e Doughboy (Ice Cube), mas cada um dos tr?s tem objetivos bem distintos na vida.",
  "genero": "CRIME, DRAMA",
  "ano": "",
  "duracao": "01:52:07",
  "elenco": "Cuba Gooding Jr., Laurence Fishburne, Ice Cube, Morris Chestnut, Angela Bassett, Nia Long, Tyra Ferrell",
  "diretor": "John Singleton",
  "titulo": "OS DONOS DA RUA",
  "id": 67455,
  "qualidade": "FHD",
  "capa_local": "OS DONOS DA RUA/OS DONOS DA RUA.jpg"
}