{
  "url": "https://guiadeconteudo.blog/movie/NjkzMjY=",
  "tipo": "filme",
  "capa_url": "https://lgfp.one/OQZ",
  "sinopse": "Quando a bibliotec?ria Taylor Harris de repente perde o emprego, volta para a sua pequena cidade natal em Montana. A?, envolve-se no combate para ajudar a salvar o pequeno hotel do irm?o do magnata Joel Sheehan, que o quer remodelar - mas as coisas acabam por se complicar quando ela se apaixona por Joel.",
  "genero": "ROMANCE, DRAMA",
  "ano": "",
  "duracao": "01:28:55",
  "elenco": "Jessica Lowndes, Chad Michael Murray, Dennis Andres, Michael Brown, Kent Sheridan, Jenni Burke, Delia Lisette Chambers",
  "diretor": "Bradley Walsh",
  "titulo": "AS CORES DO AMOR",
  "id": 102010,
  "qualidade": "FHD",
  "capa_local": "AS CORES DO AMOR/AS CORES DO AMOR.jpg"
}