{
  "url": "https://guiadeconteudo.blog/serie/OTAwMDU=",
  "tipo": "serie",
  "titulo": "A INDÚSTRIA DA CURA",
  "capa_url": "https://lgfp.one/JPT",
  "capa_local": "A INDUSTRIA DA CURA/A INDUSTRIA DA CURA.jpg",
  "sinopse": "A indústria da cura movimenta trilhões de dólares, mas será que oferece mesmo saúde, ou somos vítimas de falsas promessas? Essa série documental investiga.",
  "genero": "Documentário",
  "elenco": "",
  "diretor": "",
  "total_episodios": "55",
  "temporadas": [
    {
      "temporada": "TEMPORADA: 1",
      "episodios": [
        {
          "numero": "1",
          "codigo": "S01E01",
          "duracao": "00:54:37"
        },
        {
          "numero": "2",
          "codigo": "S01E02",
          "duracao": "00:48:23"
        },
        {
          "numero": "3",
          "codigo": "S01E03",
          "duracao": "00:52:01"
        },
        {
          "numero": "4",
          "codigo": "S01E04",
          "duracao": "00:48:45"
        },
        {
          "numero": "5",
          "codigo": "S01E05",
          "duracao": "00:57:42"
        },
        {
          "numero": "6",
          "codigo": "S01E06",
          "duracao": "00:55:33"
        }
      ]
    }
  ],
  "id": 831
}