{
  "url": "https://guiadeconteudo.blog/movie/NTUyOTY=",
  "tipo": "filme",
  "capa_url": "https://lgfp.one/EEV8",
  "sinopse": "Niki ? uma garota de 12 anos que decide visitar o seu pai que acabou de sair da pris?o. Depois de sete anos sem se verem, pai e filha descobrir?o que possuem uma conex?o muito mais forte do que imaginavam.",
  "genero": "DRAMA",
  "ano": "2021",
  "duracao": "01:38:46",
  "elenco": "Guszt?v Dietz, Zorka Horv?th, ?va F?sti Moln?r, Bal?zs Galk?, Viktor Kassai, Zsuzsa Sz?ger, Fruzsina H?da",
  "diretor": "Hajni Kis",
  "titulo": "APRENDENDO A SER PAI [L]",
  "id": 248848,
  "qualidade": "FHD",
  "capa_local": "APRENDENDO A SER PAI [L]/APRENDENDO A SER PAI [L].jpg"
}