{
  "url": "https://guiadeconteudo.blog/movie/NzI0NzY=",
  "tipo": "filme",
  "capa_url": "https://lgfp.one/RSS8",
  "sinopse": "Dois pais recebem um telefonema angustiante, tarde da noite de sua filha adolescente, que acabara de atropelar acidentalmente um pedestre. Eles entram no carro e correm para chegar l? antes que algu?m se depare com a cena. ? medida que avan?am noite adentro, revela??es perturbadoras amea?am separar a fam?lia, e logo percebem que podem n?o ser os ?nicos dirigindo pela Hallow Road.",
  "genero": "MIST?RIO, THRILLER, TERROR",
  "ano": "2025",
  "duracao": "01:20:00",
  "elenco": "Rosamund Pike, Matthew Rhys, Megan McDonnell, Tadhg Murphy, Stephen Jones",
  "diretor": "Babak Anvari",
  "titulo": "HALLOW ROAD: CAMINHO SEM VOLTA",
  "id": 361837,
  "qualidade": "FHD",
  "capa_local": "HALLOW ROAD CAMINHO SEM VOLTA/HALLOW ROAD CAMINHO SEM VOLTA.jpg"
}