{
  "url": "https://guiadeconteudo.blog/movie/NTY0NDU=",
  "tipo": "filme",
  "capa_url": "https://lgfp.one/AJV3",
  "sinopse": "Ap?s uma calamidade devastadora, uma m?e procura pelo filho desaparecido. At? descobrir que ela est? morta e presa em um reino de esp?ritos perturbados.",
  "genero": "DRAMA",
  "ano": "2024",
  "duracao": "02:12:46",
  "elenco": "?????, ?????, ????, ???, ????, ?????, Lily Franky",
  "diretor": "Michihito Fujii",
  "titulo": "A SAUDADE QUE FICA [L]",
  "id": 194941,
  "qualidade": "FHD",
  "capa_local": "A SAUDADE QUE FICA [L]/A SAUDADE QUE FICA [L].jpg"
}