{
  "url": "https://guiadeconteudo.blog/movie/NjI2MzQ=",
  "tipo": "filme",
  "capa_url": "https://lgfp.one/ROP2",
  "sinopse": "Rec?m-casados, Cynthia (Susie Abromeit) e Steve (Dillon Casey) se preparam para passar o primeiro Natal juntos e em fam?lia, mas algumas quest?es pessoais podem atrapalhar o t?o aguardado evento.",
  "genero": "COM?DIA, FAM?LIA, ROMANCE, CINEMA TV",
  "ano": "2016",
  "duracao": "01:20:24",
  "elenco": "Susie Abromeit, Dillon Casey, Erin Gray, Neil Crone, Randal Edwards",
  "diretor": "Brian K. Roberts",
  "titulo": "UM NATAL PERFEITO",
  "id": 357957,
  "qualidade": "FHD",
  "capa_local": "UM NATAL PERFEITO/UM NATAL PERFEITO.jpg"
}