{
  "url": "https://guiadeconteudo.blog/movie/NTQwNzE=",
  "tipo": "filme",
  "capa_url": "https://lgfp.one/OPT8",
  "sinopse": "\"As Crian?as de 7 de Outubro\" acompanha crian?as israelenses impactadas pelos ataques terroristas do Hamas em 7 de outubro. Liderado por Montana Tucker, o filme compartilha hist?rias de sobreviventes sequestrados, ?rf?os e traumatizados. O filme destaca o profundo impacto do terror sobre as jovens v?timas.",
  "genero": "DOCUMENT?RIO",
  "ano": "2025",
  "duracao": "00:36:12",
  "elenco": "Montana Tucker",
  "diretor": "Asaf Becker",
  "titulo": "AS CRIANÇAS DE 7 DE OUTUBRO [L]",
  "id": 307154,
  "qualidade": "FHD",
  "capa_local": "AS CRIANCAS DE 7 DE OUTUBRO [L]/AS CRIANCAS DE 7 DE OUTUBRO [L].jpg"
}