{
  "url": "https://guiadeconteudo.blog/movie/NjQ4MDk=",
  "tipo": "filme",
  "capa_url": "https://lgfp.one/IEZ",
  "sinopse": "Steven Russell ? um homem que tem uma vida feliz ao lado de sua mulher. Mas quando ele sobrevive a um grave acidente de carro, sua vida muda para sempre. Steven assume que ? gay e decide aproveitar tudo o que a vida pode lhe oferecer de melhor, nem que para isso tenha que dar alguns golpes.",
  "genero": "COM?DIA, CRIME, DRAMA, ROMANCE",
  "ano": "",
  "duracao": "01:37:29",
  "elenco": "Jim Carrey, Ewan McGregor, Leslie Mann, Rodrigo Santoro, Brennan Brown, Nicholas Alexander, Tony Bentley",
  "diretor": "Glenn Ficarra, John Requa",
  "titulo": "O GOLPISTA DO ANO",
  "id": 57326,
  "qualidade": "FHD",
  "capa_local": "O GOLPISTA DO ANO/O GOLPISTA DO ANO.jpg"
}