{
  "url": "https://guiadeconteudo.blog/movie/NTMyNzM=",
  "tipo": "filme",
  "capa_url": "https://lgfp.one/PZO9",
  "sinopse": "Um retrato do cr?tico de cinema Carlos Boyero, uma das figuras mais seguidas e temidas do cinema espanhol, cercado de pol?mica, amor e ?dio.",
  "genero": "DOCUMENT?RIO",
  "ano": "2022",
  "duracao": "01:42:00",
  "elenco": "Carlos Boyero, ?lex de la Iglesia, Enrique L?pez Lavigne, Carles Francino, Jes?s Ruiz Mantilla",
  "diretor": "Javier Morales P?rez, Juan Zavala",
  "titulo": "O CRÍTICO [L]",
  "id": 329743,
  "qualidade": "FHD",
  "capa_local": "O CRITICO [L]/O CRITICO [L].jpg"
}