{
  "url": "https://guiadeconteudo.blog/movie/NzQ5NjA=",
  "tipo": "filme",
  "capa_url": "https://lgfp.one/FWR",
  "sinopse": "Paulo de Tarso e a Hist?ria do Cristianismo Primitivo ? um filme que apresenta a vida e obra do Ap?stolo dos Gentios atrav?s da interpreta??o esp?rita dos fatos e contextos hist?ricos que envolveram esse grande personagem. Trata-se da primeira obra cinematogr?fica, produzida com o entendimento que a doutrina dos esp?ritos pode emprestar sobre ex-doutor da lei judaica, que fundou comunidades crist?s em grande parte da ?sia Menor e da Europa durante o primeiro s?culo da era Crist?.",
  "genero": "DRAMA, HIST?RIA",
  "ano": "",
  "duracao": "01:32:00",
  "elenco": "Caio Blat",
  "diretor": "Andr? Marou?o",
  "titulo": "PAULO DE TARSO E A HISTÓRIA DO CRISTIANISMO PRIMITIVO",
  "id": 4108,
  "qualidade": "FHD",
  "capa_local": "PAULO DE TARSO E A HISTORIA DO CRISTIANISMO PRIMITIVO/PAULO DE TARSO E A HISTORIA DO CRISTIANISMO PRIMITIVO.jpg"
}