{
  "url": "https://guiadeconteudo.blog/movie/NTEzNDc=",
  "tipo": "filme",
  "capa_url": "https://lgfp.one/SLV2",
  "sinopse": "Após a principal estrela de seu mais novo trabalho desistir do projeto, o produtor Viktor Taransky (Al Pacino) entra em desespero. Sem ter como deixar tudo a perder, Taransky decide criar secretamente Simone, uma atriz digital criada especialmente para o trabalho, substituindo uma de carne e osso. Mas o que Taransky não esperava era que Simone iria se tornar um sucesso mundial, sendo que todos desejam conhecê-la pessoalmente.",
  "genero": "FICÇÃO CIENTÍFICA, COMÉDIA, DRAMA, ROMANCE",
  "ano": "2002",
  "duracao": "01:57:27",
  "elenco": "Al Pacino, Rachel Roberts, Catherine Keener, Evan Rachel Wood, Jay Mohr",
  "diretor": "Andrew Niccol",
  "titulo": "SIMONE [L]",
  "id": 378980,
  "qualidade": "FHD",
  "capa_local": "SIMONE [L]/SIMONE [L].jpg"
}