{
  "url": "https://guiadeconteudo.blog/movie/NzM1NDM=",
  "tipo": "filme",
  "capa_url": "https://lgfp.one/KYO",
  "sinopse": "Quando um garoto de 12 anos desaparece, o investigador principal Greg Harper luta para equilibrar a press?o da investiga??o e os problemas com sua esposa, Jackie. Uma grande tens?o ? exercida sobre a fam?lia e lentamente consome Jackie, fazendo ela perder o controle da realidade. Mas depois que uma presen?a maliciosa se manifesta em sua casa e coloca seu filho Connor em perigo mortal, a fria e dura verdade sobre o mal na casa dos Harper ? finalmente descoberta.",
  "genero": "TERROR, THRILLER",
  "ano": "",
  "duracao": "01:37:58",
  "elenco": "Helen Hunt, Jon Tenney, Owen Teague, Judah Lewis, Libe Barer, Gregory Alan Williams, Erika Alexander",
  "diretor": "Adam Randall",
  "titulo": "À ESPREITA DO MAL",
  "id": 65257,
  "qualidade": "FHD",
  "capa_local": "A ESPREITA DO MAL/A ESPREITA DO MAL.jpg"
}