{
  "url": "https://guiadeconteudo.blog/serie/OTI5Mjg=",
  "tipo": "serie",
  "titulo": "PROTEJA SUA SORTE [L]",
  "capa_url": "https://lgfp.one/PXH4",
  "capa_local": "PROTEJA SUA SORTE [L]/PROTEJA SUA SORTE [L].jpg",
  "sinopse": "Han Mu Cheol, também conhecido como 'K-Scrooge', é dono do Edifício Daewoon e é obcecado por dinheiro. Ele é rico, mas mesquinho, tremendo por 100 won e destilando veneno nas pessoas.",
  "genero": "Família, Drama",
  "elenco": "손창민, 선우재덕, 박상면, 이아현, 오영실",
  "diretor": "",
  "total_episodios": "",
  "temporadas": [
    {
      "temporada": "TEMPORADA: 1",
      "episodios": [
        {
          "numero": "1",
          "codigo": "S01E01",
          "duracao": "00:28:30"
        },
        {
          "numero": "2",
          "codigo": "S01E02",
          "duracao": "00:28:32"
        },
        {
          "numero": "3",
          "codigo": "S01E03",
          "duracao": "00:28:47"
        },
        {
          "numero": "4",
          "codigo": "S01E04",
          "duracao": "00:28:32"
        },
        {
          "numero": "5",
          "codigo": "S01E05",
          "duracao": "00:28:49"
        },
        {
          "numero": "6",
          "codigo": "S01E06",
          "duracao": "00:28:29"
        },
        {
          "numero": "7",
          "codigo": "S01E07",
          "duracao": "00:28:30"
        },
        {
          "numero": "8",
          "codigo": "S01E08",
          "duracao": "00:28:20"
        },
        {
          "numero": "9",
          "codigo": "S01E09",
          "duracao": "00:28:26"
        },
        {
          "numero": "10",
          "codigo": "S01E10",
          "duracao": "00:28:16"
        },
        {
          "numero": "11",
          "codigo": "S01E11",
          "duracao": "00:27:33"
        },
        {
          "numero": "12",
          "codigo": "S01E12",
          "duracao": "00:28:06"
        },
        {
          "numero": "13",
          "codigo": "S01E13",
          "duracao": "00:28:29"
        },
        {
          "numero": "14",
          "codigo": "S01E14",
          "duracao": "00:28:28"
        },
        {
          "numero": "15",
          "codigo": "S01E15",
          "duracao": "00:28:27"
        },
        {
          "numero": "16",
          "codigo": "S01E16",
          "duracao": "00:28:30"
        },
        {
          "numero": "17",
          "codigo": "S01E17",
          "duracao": "00:28:29"
        },
        {
          "numero": "18",
          "codigo": "S01E18",
          "duracao": "00:28:30"
        },
        {
          "numero": "19",
          "codigo": "S01E19",
          "duracao": "00:28:28"
        },
        {
          "numero": "20",
          "codigo": "S01E20",
          "duracao": "00:28:28"
        },
        {
          "numero": "21",
          "codigo": "S01E21",
          "duracao": "00:28:27"
        },
        {
          "numero": "22",
          "codigo": "S01E22",
          "duracao": "00:28:29"
        },
        {
          "numero": "23",
          "codigo": "S01E23",
          "duracao": "00:28:28"
        },
        {
          "numero": "24",
          "codigo": "S01E24",
          "duracao": "00:28:27"
        },
        {
          "numero": "25",
          "codigo": "S01E25",
          "duracao": "00:28:32"
        },
        {
          "numero": "26",
          "codigo": "S01E26",
          "duracao": "00:27:24"
        },
        {
          "numero": "27",
          "codigo": "S01E27",
          "duracao": "00:26:32"
        },
        {
          "numero": "28",
          "codigo": "S01E28",
          "duracao": "00:27:18"
        },
        {
          "numero": "29",
          "codigo": "S01E29",
          "duracao": "00:27:20"
        },
        {
          "numero": "30",
          "codigo": "S01E30",
          "duracao": "00:27:31"
        },
        {
          "numero": "31",
          "codigo": "S01E31",
          "duracao": "00:27:27"
        },
        {
          "numero": "32",
          "codigo": "S01E32",
          "duracao": "00:26:58"
        },
        {
          "numero": "33",
          "codigo": "S01E33",
          "duracao": "00:27:11"
        },
        {
          "numero": "34",
          "codigo": "S01E34",
          "duracao": "00:27:32"
        },
        {
          "numero": "35",
          "codigo": "S01E35",
          "duracao": "00:28:18"
        },
        {
          "numero": "36",
          "codigo": "S01E36",
          "duracao": "00:28:28"
        },
        {
          "numero": "37",
          "codigo": "S01E37",
          "duracao": "00:28:28"
        },
        {
          "numero": "38",
          "codigo": "S01E38",
          "duracao": "00:28:31"
        },
        {
          "numero": "39",
          "codigo": "S01E39",
          "duracao": "00:28:29"
        },
        {
          "numero": "40",
          "codigo": "S01E40",
          "duracao": "00:28:26"
        },
        {
          "numero": "41",
          "codigo": "S01E41",
          "duracao": "00:28:08"
        },
        {
          "numero": "42",
          "codigo": "S01E42",
          "duracao": "00:28:31"
        },
        {
          "numero": "43",
          "codigo": "S01E43",
          "duracao": "00:28:28"
        },
        {
          "numero": "44",
          "codigo": "S01E44",
          "duracao": "00:28:19"
        },
        {
          "numero": "45",
          "codigo": "S01E45",
          "duracao": "00:28:25"
        },
        {
          "numero": "46",
          "codigo": "S01E46",
          "duracao": "00:28:15"
        },
        {
          "numero": "47",
          "codigo": "S01E47",
          "duracao": "00:28:31"
        },
        {
          "numero": "48",
          "codigo": "S01E48",
          "duracao": "00:28:16"
        },
        {
          "numero": "49",
          "codigo": "S01E49",
          "duracao": "00:28:06"
        },
        {
          "numero": "50",
          "codigo": "S01E50",
          "duracao": "00:28:26"
        },
        {
          "numero": "51",
          "codigo": "S01E51",
          "duracao": "00:28:13"
        },
        {
          "numero": "52",
          "codigo": "S01E52",
          "duracao": "00:28:31"
        },
        {
          "numero": "53",
          "codigo": "S01E53",
          "duracao": "00:28:26"
        },
        {
          "numero": "54",
          "codigo": "S01E54",
          "duracao": "00:28:26"
        },
        {
          "numero": "55",
          "codigo": "S01E55",
          "duracao": "00:28:07"
        },
        {
          "numero": "56",
          "codigo": "S01E56",
          "duracao": "00:28:28"
        },
        {
          "numero": "57",
          "codigo": "S01E57",
          "duracao": "00:28:13"
        },
        {
          "numero": "58",
          "codigo": "S01E58",
          "duracao": "00:28:24"
        },
        {
          "numero": "59",
          "codigo": "S01E59",
          "duracao": "00:28:08"
        },
        {
          "numero": "60",
          "codigo": "S01E60",
          "duracao": "00:28:04"
        },
        {
          "numero": "61",
          "codigo": "S01E61",
          "duracao": "00:28:26"
        },
        {
          "numero": "62",
          "codigo": "S01E62",
          "duracao": "00:28:31"
        },
        {
          "numero": "63",
          "codigo": "S01E63",
          "duracao": "00:28:10"
        },
        {
          "numero": "64",
          "codigo": "S01E64",
          "duracao": "00:28:17"
        },
        {
          "numero": "65",
          "codigo": "S01E65",
          "duracao": "00:28:25"
        },
        {
          "numero": "66",
          "codigo": "S01E66",
          "duracao": "00:28:31"
        },
        {
          "numero": "67",
          "codigo": "S01E67",
          "duracao": "00:28:14"
        },
        {
          "numero": "68",
          "codigo": "S01E68",
          "duracao": "00:28:32"
        },
        {
          "numero": "69",
          "codigo": "S01E69",
          "duracao": "00:27:57"
        },
        {
          "numero": "70",
          "codigo": "S01E70",
          "duracao": "00:27:58"
        },
        {
          "numero": "71",
          "codigo": "S01E71",
          "duracao": "00:27:59"
        },
        {
          "numero": "72",
          "codigo": "S01E72",
          "duracao": "00:28:13"
        },
        {
          "numero": "73",
          "codigo": "S01E73",
          "duracao": "00:28:09"
        },
        {
          "numero": "74",
          "codigo": "S01E74",
          "duracao": "00:28:09"
        },
        {
          "numero": "75",
          "codigo": "S01E75",
          "duracao": "00:28:27"
        },
        {
          "numero": "76",
          "codigo": "S01E76",
          "duracao": "00:28:23"
        },
        {
          "numero": "77",
          "codigo": "S01E77",
          "duracao": "00:28:20"
        },
        {
          "numero": "78",
          "codigo": "S01E78",
          "duracao": "00:28:26"
        },
        {
          "numero": "79",
          "codigo": "S01E79",
          "duracao": "00:28:29"
        },
        {
          "numero": "80",
          "codigo": "S01E80",
          "duracao": "00:27:45"
        },
        {
          "numero": "81",
          "codigo": "S01E81",
          "duracao": "00:27:58"
        },
        {
          "numero": "82",
          "codigo": "S01E82",
          "duracao": "00:28:29"
        },
        {
          "numero": "83",
          "codigo": "S01E83",
          "duracao": "00:27:44"
        },
        {
          "numero": "84",
          "codigo": "S01E84",
          "duracao": "00:28:27"
        },
        {
          "numero": "85",
          "codigo": "S01E85",
          "duracao": "00:28:29"
        },
        {
          "numero": "86",
          "codigo": "S01E86",
          "duracao": "00:28:31"
        },
        {
          "numero": "87",
          "codigo": "S01E87",
          "duracao": "00:28:33"
        },
        {
          "numero": "88",
          "codigo": "S01E88",
          "duracao": "00:28:33"
        },
        {
          "numero": "89",
          "codigo": "S01E89",
          "duracao": "00:28:08"
        },
        {
          "numero": "90",
          "codigo": "S01E90",
          "duracao": "00:28:12"
        },
        {
          "numero": "91",
          "codigo": "S01E91",
          "duracao": "00:28:10"
        },
        {
          "numero": "92",
          "codigo": "S01E92",
          "duracao": "00:28:11"
        },
        {
          "numero": "93",
          "codigo": "S01E93",
          "duracao": "00:27:55"
        },
        {
          "numero": "94",
          "codigo": "S01E94",
          "duracao": "00:28:05"
        },
        {
          "numero": "95",
          "codigo": "S01E95",
          "duracao": "00:28:05"
        },
        {
          "numero": "96",
          "codigo": "S01E96",
          "duracao": "00:28:07"
        },
        {
          "numero": "97",
          "codigo": "S01E97",
          "duracao": "00:28:08"
        },
        {
          "numero": "98",
          "codigo": "S01E98",
          "duracao": "00:28:17"
        },
        {
          "numero": "99",
          "codigo": "S01E99",
          "duracao": "00:28:18"
        },
        {
          "numero": "100",
          "codigo": "S01E100",
          "duracao": "00:28:18"
        },
        {
          "numero": "101",
          "codigo": "S01E101",
          "duracao": "00:28:17"
        },
        {
          "numero": "102",
          "codigo": "S01E102",
          "duracao": "00:28:31"
        },
        {
          "numero": "103",
          "codigo": "S01E103",
          "duracao": "00:28:19"
        },
        {
          "numero": "104",
          "codigo": "S01E104",
          "duracao": "00:28:27"
        },
        {
          "numero": "105",
          "codigo": "S01E105",
          "duracao": "00:28:29"
        },
        {
          "numero": "106",
          "codigo": "S01E106",
          "duracao": "00:28:25"
        },
        {
          "numero": "107",
          "codigo": "S01E107",
          "duracao": "00:28:24"
        },
        {
          "numero": "108",
          "codigo": "S01E108",
          "duracao": "00:28:02"
        },
        {
          "numero": "109",
          "codigo": "S01E109",
          "duracao": "00:28:29"
        },
        {
          "numero": "110",
          "codigo": "S01E110",
          "duracao": "00:28:18"
        },
        {
          "numero": "111",
          "codigo": "S01E111",
          "duracao": "00:28:04"
        },
        {
          "numero": "112",
          "codigo": "S01E112",
          "duracao": "00:28:12"
        },
        {
          "numero": "113",
          "codigo": "S01E113",
          "duracao": "00:27:56"
        },
        {
          "numero": "114",
          "codigo": "S01E114",
          "duracao": "00:27:51"
        },
        {
          "numero": "115",
          "codigo": "S01E115",
          "duracao": "00:28:00"
        },
        {
          "numero": "116",
          "codigo": "S01E116",
          "duracao": "00:28:00"
        },
        {
          "numero": "117",
          "codigo": "S01E117",
          "duracao": "00:27:42"
        },
        {
          "numero": "118",
          "codigo": "S01E118",
          "duracao": "00:28:34"
        },
        {
          "numero": "119",
          "codigo": "S01E119",
          "duracao": "00:28:06"
        },
        {
          "numero": "120",
          "codigo": "S01E120",
          "duracao": "00:28:25"
        },
        {
          "numero": "121",
          "codigo": "S01E121",
          "duracao": "00:29:11"
        }
      ]
    }
  ],
  "id": 7939
}