{
  "url": "https://guiadeconteudo.blog/movie/NjY2NjI=",
  "tipo": "filme",
  "capa_url": "https://lgfp.one/EVS",
  "sinopse": "Este ? mais um cl?ssico de mudan?as no clima das regi?es al?m do Grande Vale. A terra ressecada transformou-se na \"Terra das Brumas\". Novas e estranhas criaturas come?aram a aparecer, e outras se mudaram para as ?rvores mais altas, de cujas folhas os dinossauros se alimentam. Felizmente, o Vale continua bonito como sempre, e n?o ? preciso enfrentar as terras ?midas... At? o dia em que o av? de Littlefoot fica doente. A ?nica esperan?a de cura ? comer as p?talas douradas de \"Flor da Noite\", que s? nasce na \"Terra das Brumas\". Agora Littlefoot e seus amigos precisam explorar os p?ntanos, enfrentar os novos vil?es e encontrar a Flor, a tempo de salvar o vov?. Durante sua miss?o, eles v?o aprender algumas ador?veis li??es, sobre coopera??o, solidariedade e a mais importante de todas: que ? ?timo ter amigos de todos os tipos, de todas as formas e tamanhos.",
  "genero": "AVENTURA, ANIMA??O, COM?DIA, FAM?LIA",
  "ano": "",
  "duracao": "01:13:52",
  "elenco": "John Ingle, Candace Hutson, Heather Hogan, Rob Paulsen, Jeff Bennett, Scott McAfee, Kenneth Mars",
  "diretor": "Roy Allen Smith",
  "titulo": "EM BUSCA DO VALE ENCANTADO IV: VIAGEM ATRAVÉS DA NÉVOA",
  "id": 3304,
  "qualidade": "FHD",
  "capa_local": "EM BUSCA DO VALE ENCANTADO IV VIAGEM ATRAVES DA NEVOA/EM BUSCA DO VALE ENCANTADO IV VIAGEM ATRAVES DA NEVOA.jpg"
}