{
  "url": "https://guiadeconteudo.blog/movie/ODYyNTM=",
  "tipo": "filme",
  "capa_url": "https://lgfp.one/ROW6",
  "sinopse": "Especialistas em tubar?es mergulham em uma regi?o de grande atividade de tubar?es-brancos rec?m-descoberta na Calif?rnia e na ilha de Guadalupe para dar uma estimativa da popula??o de tubar?es-brancos.",
  "genero": "DOCUMENT?RIO, CINEMA TV",
  "ano": "2022",
  "duracao": "00:44:00",
  "elenco": "Jack Dennis, Nicole Nasby-Lucas, Nehaacharya Patel, Keith Poe",
  "diretor": "",
  "titulo": "MANDÍBULAS À ESPREITA",
  "id": 358399,
  "qualidade": "FHD",
  "capa_local": "MANDIBULAS A ESPREITA/MANDIBULAS A ESPREITA.jpg"
}