{
  "url": "https://guiadeconteudo.blog/movie/NjczMjY=",
  "tipo": "filme",
  "capa_url": "https://lgfp.one/SAD6",
  "sinopse": "Em Nova York, Ruth (Diane Keaton) e Alex (Morgan Freeman), juntos h? d?cadas, decidem vender o apartamento onde sempre viveram no Brooklyn e ir para um outro lugar. Eles apenas n?o imaginam a quantidade de problemas que v?o encontrar nas negocia??es para se desfazer do im?vel que compraram na d?cada de 1970.",
  "genero": "DRAMA",
  "ano": "2014",
  "duracao": "01:32:24",
  "elenco": "Morgan Freeman, Diane Keaton, Carrie Preston, Cynthia Nixon, Alysia Reiner",
  "diretor": "Richard Loncraine",
  "titulo": "RUTH E ALEX",
  "id": 370198,
  "qualidade": "FHD",
  "capa_local": "RUTH E ALEX/RUTH E ALEX.jpg"
}