{
  "url": "https://guiadeconteudo.blog/serie/OTMxODE=",
  "tipo": "serie",
  "titulo": "FAMILIA POR ESCOLHA [L]",
  "capa_url": "https://lgfp.one/DXN6",
  "capa_local": "FAMILIA POR ESCOLHA [L]/FAMILIA POR ESCOLHA [L].jpg",
  "sinopse": "Apesar de não serem parentes, Kim San-ha, Yun Ju-won e Kang Hae-jun compartilham um vínculo estreito entre si. Eles foram criados juntos por Jeong Jae, pai de Ju-won, e pelo pai de San-ha, Dae Uk, que fizeram o possível para proporcionar-lhes uma infância feliz enquanto se curavam de traumas do passado. Ao atingir a idade adulta, porém, San-ha e Hae-jun procuraram suas famílias biológicas, fazendo Ju-won sentir-se abandonada. Dez anos depois, os três se reencontram, mas as coisas não são mais as mesmas. Agora, eles terão de aprender a esquecer as mágoas do passado, e os meninos terão que lidar com os sentimentos que nutrem por Ju-won.",
  "genero": "Drama, Família",
  "elenco": "황인엽, 정채연, 배현성, 최원영, 최무성",
  "diretor": "Kim Seung-ho",
  "total_episodios": "70",
  "temporadas": [
    {
      "temporada": "TEMPORADA: 1",
      "episodios": [
        {
          "numero": "1",
          "codigo": "S01E01",
          "duracao": "01:02:31"
        },
        {
          "numero": "2",
          "codigo": "S01E02",
          "duracao": "01:07:58"
        },
        {
          "numero": "3",
          "codigo": "S01E03",
          "duracao": "01:01:35"
        },
        {
          "numero": "4",
          "codigo": "S01E04",
          "duracao": "01:00:45"
        },
        {
          "numero": "5",
          "codigo": "S01E05",
          "duracao": "01:00:05"
        },
        {
          "numero": "6",
          "codigo": "S01E06",
          "duracao": "01:00:35"
        },
        {
          "numero": "7",
          "codigo": "S01E07",
          "duracao": "01:02:57"
        },
        {
          "numero": "8",
          "codigo": "S01E08",
          "duracao": "01:02:10"
        },
        {
          "numero": "9",
          "codigo": "S01E09",
          "duracao": "01:05:17"
        },
        {
          "numero": "10",
          "codigo": "S01E10",
          "duracao": "00:59:40"
        },
        {
          "numero": "11",
          "codigo": "S01E11",
          "duracao": "01:02:57"
        },
        {
          "numero": "12",
          "codigo": "S01E12",
          "duracao": "01:01:29"
        },
        {
          "numero": "13",
          "codigo": "S01E13",
          "duracao": "01:04:28"
        },
        {
          "numero": "14",
          "codigo": "S01E14",
          "duracao": "01:05:07"
        },
        {
          "numero": "15",
          "codigo": "S01E15",
          "duracao": "01:01:04"
        },
        {
          "numero": "16",
          "codigo": "S01E16",
          "duracao": "01:03:48"
        }
      ]
    }
  ],
  "id": 6127
}