{
  "url": "https://guiadeconteudo.blog/movie/NzI3MjE=",
  "tipo": "filme",
  "capa_url": "https://lgfp.one/PRE8",
  "sinopse": "O embaixador americano e a esposa querem muito ter filhos. Quando ela d? ? luz um beb? morto e um padre sugere que adotem um rec?m-nascido saud?vel e ?rf?o, ele aceita sem contar ? mulher. O que ele n?o sabe ? que o beb? ? o anticristo.",
  "genero": "TERROR, THRILLER",
  "ano": "1976",
  "duracao": "01:51:00",
  "elenco": "Gregory Peck, Lee Remick, David Warner, Billie Whitelaw, Harvey Stephens",
  "diretor": "Richard Donner",
  "titulo": "A PROFECIA",
  "id": 322123,
  "qualidade": "FHD",
  "capa_local": "A PROFECIA/A PROFECIA.jpg"
}