{
  "url": "https://guiadeconteudo.blog/movie/NjcwNDk=",
  "tipo": "filme",
  "capa_url": "https://lgfp.one/KDK",
  "sinopse": "Voc? gostaria de viajar ao mundo atrav?s do espelho? O universo de BIA est? totalmente revirado. Os personagens s?o os mesmos, mas seus comportamentos s?o opostos aos habituais. Uma viagem a uma dimens?o paralela onde os her?is s?o vil?es e vice e versa.",
  "genero": "COM?DIA, DRAMA, FAM?LIA",
  "ano": "",
  "duracao": "01:31:41",
  "elenco": "Isabela Souza, Julio Pe?a, Gabriella Di Grecco, Andrea de Alba, Guido Messina, Fernando Dente, Rhener Freitas",
  "diretor": "Jorge Bechara",
  "titulo": "BIA: UM MUNDO DO AVESSO",
  "id": 62341,
  "qualidade": "FHD",
  "capa_local": "BIA UM MUNDO DO AVESSO/BIA UM MUNDO DO AVESSO.jpg"
}