{
  "url": "https://guiadeconteudo.blog/movie/NzA5OTU=",
  "tipo": "filme",
  "capa_url": "https://lgfp.one/QNJ8",
  "sinopse": "O Xerife de Nottingham planeja confiscar a propriedade do Senhor de Bawtry, um nobre que morreu na Cruzada. O Arcebispo de Canterbury, Hubert Walter, ? contra este plano e o xerife planeja elimin?-lo. Robin Hood ? convidado a realizar o assassinato do arcebispo para os conspiradores, liderados pelo Conde de Newark e Lord Melton, mas, ao perceber quem ? o alvo pretendido, resolve ajudar o Arcebispo. Lady Marian tamb?m quer conhecer o Arcebispo para que ela possa conceder liberdade ? fam?lia de um homem assassinado pelos homens do Xerife e ela tamb?m est? ansiosa para encontrar Robin novamente, pois o conheceu quando achava que ele era um fora da lei comum, mas agora percebe que ele est? do lado do bem.",
  "genero": "AVENTURA, HIST?RIA",
  "ano": "1960",
  "duracao": "01:19:56",
  "elenco": "Richard Greene, Peter Cushing, Niall MacGinnis, Richard Pasco, Jack Gwillim",
  "diretor": "Terence Fisher",
  "titulo": "ROBIN HOOD – O INVENCÍVEL",
  "id": 340816,
  "qualidade": "FHD",
  "capa_local": "ROBIN HOOD  O INVENCIVEL/ROBIN HOOD  O INVENCIVEL.jpg"
}