{
  "url": "https://guiadeconteudo.blog/movie/NjEzNjQ=",
  "tipo": "filme",
  "capa_url": "https://lgfp.one/NPO",
  "sinopse": "No s?culo XIX, um navio naufraga perto da selva africana e um casal consegue chegar em terra firme. A mulher estava gr?vida e tem seu filho em uma casa nas ?rvores. Algum tempo depois os pais do menino s?o mortos por animais e ele ? criado por uma macaca, que tinha perdido seu filhote. Ele cresce como se fosse um s?mio, mas ap?s vinte anos, ele ? descoberto e volta a civiliza??o, onde ? herdeiro de uma grande fortuna. Mas a adapta??o com esta nova realidade ? estranha demais para ele.",
  "genero": "AVENTURA, DRAMA, A??O, ROMANCE",
  "ano": "",
  "duracao": "02:23:00",
  "elenco": "Christopher Lambert, Andie MacDowell, Ralph Richardson, Ian Holm, James Fox, Cheryl Campbell, Ian Charleson",
  "diretor": "Hugh Hudson",
  "titulo": "GREYSTOKE - A LENDA DE TARZAN, O REI DA SELVA",
  "id": 94606,
  "qualidade": "FHD",
  "capa_local": "GREYSTOKE - A LENDA DE TARZAN, O REI DA SELVA/GREYSTOKE - A LENDA DE TARZAN, O REI DA SELVA.jpg"
}