{
  "url": "https://guiadeconteudo.blog/movie/NzIxNzE=",
  "tipo": "filme",
  "capa_url": "https://lgfp.one/QYF",
  "sinopse": "A investigadora Tess ? convidada para participar de um game show popular, mas o apresentador ? inesperadamente assassinado. Cabe a ela e ao detetive Logan O'Connor tentarem descobrir o culpado.",
  "genero": "CINEMA TV, MIST?RIO, CRIME, DRAMA",
  "ano": "",
  "duracao": "",
  "elenco": "Lacey Chabert, Brennan Elliott, Barbara Niven, John Kapelos, Jon Cor, Parveen Dosanjh, Lucia Walters",
  "diretor": "David Winning",
  "titulo": "MISTÉRIO DAS PALAVRAS CRUZADAS: ENIGMA MORTAL",
  "id": 120164,
  "qualidade": "FHD",
  "capa_local": "MISTERIO DAS PALAVRAS CRUZADAS ENIGMA MORTAL/MISTERIO DAS PALAVRAS CRUZADAS ENIGMA MORTAL.jpg"
}